{
  "title": "148863790.an Existential Post",
  "slug": "148863790an-existential-post",
  "publishedAt": "2025-11-30T19:30:08.499Z",
  "excerpt": "I was having a conversation with a friend about how much time I’ve managed to waste this past year on useless, fruitless endeavors.",
  "image": "",
  "readTime": "1 min",
  "content": [
    {
      "_type": "block",
      "style": "normal",
      "children": [
        {
          "_type": "span",
          "text": "I was having a conversation with a friend about how much time I’ve managed to waste this past year on useless, fruitless endeavors.",
          "marks": []
        }
      ]
    },
    {
      "_type": "block",
      "style": "normal",
      "children": [
        {
          "_type": "span",
          "text": "“It’s all been a colossal waste of time,” I commented.",
          "marks": []
        }
      ]
    },
    {
      "_type": "block",
      "style": "normal",
      "children": [
        {
          "_type": "span",
          "text": "He turned to me, and, half jokingly, asked,",
          "marks": []
        },
        {
          "_type": "span",
          "text": "“what isn’t?”",
          "marks": []
        }
      ]
    },
    {
      "_type": "block",
      "style": "normal",
      "children": [
        {
          "_type": "span",
          "text": "What matters is what we",
          "marks": []
        },
        {
          "_type": "span",
          "text": "do",
          "marks": []
        },
        {
          "_type": "span",
          "text": "in the context of all that wasted time.",
          "marks": []
        }
      ]
    }
  ]
}