{
  "title": "148862819.gravitas And Sprezzatura",
  "slug": "148862819gravitas-and-sprezzatura",
  "publishedAt": "2025-11-30T19:29:50.550Z",
  "excerpt": "I once had a teacher who said that the secret to being treated like a professional was to exemplify “gravitas” and “sprezzatura.”",
  "image": "",
  "readTime": "1 min",
  "content": [
    {
      "_type": "block",
      "style": "normal",
      "children": [
        {
          "_type": "span",
          "text": "I once had a teacher who said that the secret to being treated like a professional was to exemplify “gravitas” and “sprezzatura.”",
          "marks": []
        }
      ]
    },
    {
      "_type": "block",
      "style": "normal",
      "children": [
        {
          "_type": "span",
          "text": "In other words, to carry yourself with an air of “solemn carelessness.”",
          "marks": []
        }
      ]
    },
    {
      "_type": "block",
      "style": "normal",
      "children": [
        {
          "_type": "span",
          "text": "She then explained how she purchased a “new Coach purse every year” to give the impression that she meant business.",
          "marks": []
        }
      ]
    },
    {
      "_type": "block",
      "style": "normal",
      "children": [
        {
          "_type": "span",
          "text": "Frankly, I don’t think that’s very good advice.",
          "marks": []
        }
      ]
    },
    {
      "_type": "block",
      "style": "normal",
      "children": [
        {
          "_type": "span",
          "text": "I think if that if you want to be treated with respect, you should earn it.",
          "marks": []
        }
      ]
    },
    {
      "_type": "block",
      "style": "normal",
      "children": [
        {
          "_type": "span",
          "text": "And if you want to feel confident, you need experience.",
          "marks": []
        }
      ]
    },
    {
      "_type": "block",
      "style": "normal",
      "children": [
        {
          "_type": "span",
          "text": "Perhaps a better word-pair might be “perspicacity and preparedness.”",
          "marks": []
        }
      ]
    },
    {
      "_type": "block",
      "style": "normal",
      "children": [
        {
          "_type": "span",
          "text": "Perspicacity as in ‘penetrating insight’, as in ‘maybe I don’t a $400 purse to feel accomplished.’",
          "marks": []
        }
      ]
    },
    {
      "_type": "block",
      "style": "normal",
      "children": [
        {
          "_type": "span",
          "text": "And preparedness, because confidence is a by-product of exposure, of going first, and most importantly, being so good you have little reason to question your ability.",
          "marks": []
        }
      ]
    },
    {
      "_type": "block",
      "style": "normal",
      "children": [
        {
          "_type": "span",
          "text": "With little doubt, being so good they can’t ignore you is the best way to ensure that you aren’t.",
          "marks": []
        }
      ]
    }
  ]
}