{
  "title": "148862838.half Way Around The World From You",
  "slug": "148862838half-way-around-the-world-from-you",
  "publishedAt": "2025-11-30T19:29:51.026Z",
  "excerpt": "…is likely someone who can do what you’re good at, better than you can.",
  "image": "",
  "readTime": "1 min",
  "content": [
    {
      "_type": "block",
      "style": "normal",
      "children": [
        {
          "_type": "span",
          "text": "…is likely someone who can do what you’re good at, better than you can.",
          "marks": []
        }
      ]
    },
    {
      "_type": "block",
      "style": "normal",
      "children": [
        {
          "_type": "span",
          "text": "Give that person the leverage the internet now enables, and you might find yourself competiting for the same job.",
          "marks": []
        }
      ]
    },
    {
      "_type": "block",
      "style": "normal",
      "children": [
        {
          "_type": "span",
          "text": "The lesson here isn’t that outsourcing is a bad thing. (It’s actually a great thing.)",
          "marks": []
        }
      ]
    },
    {
      "_type": "block",
      "style": "normal",
      "children": [
        {
          "_type": "span",
          "text": "The lesson is that if you don’t want to be replaceable, you have to find a way not to be. To do a thing (or a host things) unlike anyone else.",
          "marks": []
        }
      ]
    },
    {
      "_type": "block",
      "style": "normal",
      "children": [
        {
          "_type": "span",
          "text": "Because as it turns out, you don’t have to be the best in world to hold a job or to make an impact. You just have to be irreplaceable to the small corner of the world that needs you.",
          "marks": []
        }
      ]
    }
  ]
}