{
  "title": "Is it good enough",
  "slug": "is-it-good-enough",
  "publishedAt": "2019-10-11T06:21:23.000Z",
  "excerpt": "It's all too easy to get caught up in making things perfect, incessantly checking for mistakes and errors and nit-picky details of all kinds.",
  "image": "",
  "readTime": "1 min",
  "content": [
    {
      "_type": "block",
      "style": "normal",
      "children": [
        {
          "_type": "span",
          "text": "It's all too easy to get caught up in making things perfect, incessantly checking for mistakes and errors and nit-picky details of all kinds.",
          "marks": []
        }
      ]
    },
    {
      "_type": "block",
      "style": "normal",
      "children": [
        {
          "_type": "span",
          "text": "To make edits all day long...until you're numb from feeling like this thing, this project, is absolutely perfect.",
          "marks": []
        }
      ]
    },
    {
      "_type": "block",
      "style": "normal",
      "children": [
        {
          "_type": "span",
          "text": "Thing is, perfection isn't the point. Creating forward motion, shipping this project, changing someone for the better...my guess is that ",
          "marks": []
        },
        {
          "_type": "span",
          "text": "this",
          "marks": []
        },
        {
          "_type": "span",
          "text": " is what you're all about.",
          "marks": []
        }
      ]
    },
    {
      "_type": "block",
      "style": "normal",
      "children": [
        {
          "_type": "span",
          "text": "But if all you do today is make notes of things that need to be addressed later--tomorrow--you'll never ship. You'll merely stall and lag behind.",
          "marks": []
        }
      ]
    },
    {
      "_type": "block",
      "style": "normal",
      "children": [
        {
          "_type": "span",
          "text": "The alternative is to accept that 'good enough' isn't something to avoid, but something to embrace.",
          "marks": []
        }
      ]
    },
    {
      "_type": "block",
      "style": "normal",
      "children": [
        {
          "_type": "span",
          "text": "'Good enough' is how you escape the trap of faultlessness. Because, after all, nothing is ever good enough to be perfect.",
          "marks": []
        }
      ]
    }
  ]
}