{
  "title": "The problem with copying your competitors",
  "slug": "the-problem-with-copying-your-competitors",
  "publishedAt": "2023-04-06T06:00:00.000Z",
  "excerpt": "Actually, there are two problems.",
  "image": "",
  "readTime": "1 min",
  "content": [
    {
      "_type": "block",
      "style": "normal",
      "children": [
        {
          "_type": "span",
          "text": "Actually, there are two problems.",
          "marks": []
        }
      ]
    },
    {
      "_type": "block",
      "style": "normal",
      "children": [
        {
          "_type": "span",
          "text": "One, it assumes that your competitors know what they’re doing or that they’re applying the same considerations as you are in tackling a problem.",
          "marks": []
        }
      ]
    },
    {
      "_type": "block",
      "style": "normal",
      "children": [
        {
          "_type": "span",
          "text": "Two, assuming that they really have the same resources, it assumes that they ostensibly know more than you. (Even though they might as well have copied from what came before, as well.)",
          "marks": []
        }
      ]
    }
  ]
}