{
  "title": "What are your five rules",
  "slug": "what-are-your-five-rules",
  "publishedAt": "2018-06-10T12:06:40.000Z",
  "excerpt": "One way to think about how to achieve success in any endeavor is to think about it in terms of following the most straightforward path.",
  "image": "",
  "readTime": "1 min",
  "content": [
    {
      "_type": "block",
      "style": "normal",
      "children": [
        {
          "_type": "span",
          "text": "One way to think about how to achieve success in any endeavor is to think about it in terms of following the most straightforward path.",
          "marks": []
        }
      ]
    },
    {
      "_type": "block",
      "style": "normal",
      "children": [
        {
          "_type": "span",
          "text": "What’s going to get me from point A to point B in the fastest most efficient way possible?",
          "marks": []
        }
      ]
    },
    {
      "_type": "block",
      "style": "normal",
      "children": [
        {
          "_type": "span",
          "text": "If you can pin-point exactly what you need to do to get to where you want to be, where all you have to do is follow a linear path, then, it’s a lot easier to figure out how to get there.",
          "marks": []
        }
      ]
    },
    {
      "_type": "block",
      "style": "normal",
      "children": [
        {
          "_type": "span",
          "text": "Because then the hardest part isn’t determining what you should be doing, it’s merely figuring out what’s holding you back from consistently following the rules that make success possible.",
          "marks": []
        }
      ]
    },
    {
      "_type": "block",
      "style": "normal",
      "children": [
        {
          "_type": "span",
          "text": "If it were as simple as following five simple rules, would you do it?",
          "marks": []
        }
      ]
    }
  ]
}